mondobrain/__init__.py
mondobrain/bot.py
mondobrain/conftest.py
mondobrain/dd_transformer.py
mondobrain/error.py
mondobrain/prescriber.py
mondobrain/api/__init__.py
mondobrain/api/api.py
mondobrain/api/auth.py
mondobrain/api/clients.py
mondobrain/api/language.py
mondobrain/api/meta.py
mondobrain/api/requestor.py
mondobrain/api/solve.py
mondobrain/api/util.py
mondobrain/core/__init__.py
mondobrain/core/api.py
mondobrain/core/frame.py
mondobrain/core/meta.py
mondobrain/core/series.py
mondobrain/datasets/__init__.py
mondobrain/datasets/_base.py
mondobrain/datasets/data/bank-credit-risk-with-date.csv
mondobrain/datasets/data/bronchial-risk.csv
mondobrain/datasets/data/iris.csv
mondobrain/datasets/data/jets.csv
mondobrain/datasets/data/mazda.csv
mondobrain/datasets/data/political-behavior.csv
mondobrain/datasets/data/shampoo.csv
mondobrain/datasets/data/titanic.csv
mondobrain/datautils/__init__.py
mondobrain/datautils/_apply.py
mondobrain/datautils/_decorrelate.py
mondobrain/datautils/_sample.py
mondobrain/diagnostics/__init__.py
mondobrain/diagnostics/_extraction.py
mondobrain/diagnostics/_validation.py
mondobrain/examples/import.md
mondobrain/metrics/__init__.py
mondobrain/metrics/_bias.py
mondobrain/metrics/_correlation.py
mondobrain/metrics/_encoded.py
mondobrain/metrics/_score.py
mondobrain/metrics/_target.py
mondobrain/solver/__init__.py
mondobrain/solver/_solver.py
mondobrain/solver/meta/__init__.py
mondobrain/solver/meta/_solve.py
mondobrain/utils/__init__.py
mondobrain/utils/constants.py
mondobrain/utils/data.py
mondobrain/utils/graph.py
mondobrain/utils/graphviz.py
mondobrain/utils/log.py
mondobrain/utils/meta.py
mondobrain/utils/utilities.py
mondobrain-0.2.0.dist-info/LICENSE
mondobrain-0.2.0.dist-info/METADATA
mondobrain-0.2.0.dist-info/WHEEL
mondobrain-0.2.0.dist-info/top_level.txt
mondobrain-0.2.0.dist-info/RECORD
