Metadata-Version: 2.1
Name: mondobrain
Version: 0.2.0
Summary: MondoBrain API wrapper
Home-page: https://bitbucket.org/mondobrain/mondobrain-python
Author: MondoBrain
License: MIT License
Project-URL: MondoBrain homepage, https://mondobrain.com
Project-URL: MondoBrain source, https://bitbucket.org/mondobrain/mondobrain-python
Platform: any
Classifier: Development Status :: 3 - Alpha
Classifier: Intended Audience :: Developers
Classifier: Topic :: Software Development
Classifier: Topic :: Scientific/Engineering
Classifier: Natural Language :: English
Classifier: License :: OSI Approved :: MIT License
Classifier: Programming Language :: Python :: 3
Classifier: Programming Language :: Python :: 3.5
Classifier: Programming Language :: Python :: 3.6
Classifier: Programming Language :: Python :: 3.7
Classifier: Programming Language :: Python :: 3.8
Classifier: Operating System :: OS Independent
Classifier: Operating System :: Microsoft :: Windows
Classifier: Operating System :: POSIX
Classifier: Operating System :: Unix
Classifier: Operating System :: MacOS
Requires-Python: >=3.6
License-File: LICENSE
Requires-Dist: auth0-python (~=3.13.0)
Requires-Dist: networkx (~=2.5)
Requires-Dist: numpy (~=1.18)
Requires-Dist: pandas (~=1.0)
Requires-Dist: pyarrow (~=0.16.0)
Requires-Dist: requests (~=2.7)
Requires-Dist: scikit-learn (~=0.22.1)
Provides-Extra: viz
Requires-Dist: graphviz (~=0.14.2) ; extra == 'viz'
Requires-Dist: pygraphviz (~=1.6) ; extra == 'viz'
